src/js/mediasorter/dist/assets/flUhRq6tzZclQEJ-Vdg-IuiaDsNa-fd84f88b.woff
src/js/mediasorter/dist/assets/flUhRq6tzZclQEJ-Vdg-IuiaDsNcIhQ8tQ-4a4dbc62.woff2
src/js/mediasorter/dist/assets/index-a15cb976.js
src/js/mediasorter/dist/assets/index-d0a65fba.css
src/js/mediasorter/dist/favicon.ico
src/js/mediasorter/dist/index.html
api/__init__.py
api/app.py
mediasorter_server-0.1.4.dist-info/LICENSE
mediasorter_server-0.1.4.dist-info/METADATA
mediasorter_server-0.1.4.dist-info/WHEEL
mediasorter_server-0.1.4.dist-info/entry_points.txt
mediasorter_server-0.1.4.dist-info/RECORD
