Metadata-Version: 2.1
Name: mediasorter-server
Version: 0.1.4
Summary: 
License: MIT
Author: Your Name
Author-email: you@example.com
Requires-Python: >=3.11,<4.0
Classifier: License :: OSI Approved :: MIT License
Classifier: Programming Language :: Python :: 3
Classifier: Programming Language :: Python :: 3.11
Classifier: Programming Language :: Python :: 3.12
Requires-Dist: fastapi (>=0.104.1,<0.105.0)
Requires-Dist: multimediasorter (>=1.4.0,<2.0.0)
Requires-Dist: python-dotenv (>=1.0.0,<2.0.0)
Requires-Dist: uvicorn (>=0.24.0.post1,<0.25.0)
